gitevo/__init__.py
gitevo/__main__.py
gitevo/application.py
gitevo/cli.py
gitevo/exceptions.py
gitevo/info.py
gitevo/model.py
gitevo/report_csv.py
gitevo/report_html.py
gitevo/template.html
gitevo/utils.py
gitevo/reports/__init__.py
gitevo/reports/java.py
gitevo/reports/javascript.py
gitevo/reports/python.py
gitevo/reports/python_fastapi.py
gitevo/reports/typescript.py
gitevo-0.1.3.dist-info/METADATA
gitevo-0.1.3.dist-info/WHEEL
gitevo-0.1.3.dist-info/entry_points.txt
gitevo-0.1.3.dist-info/licenses/LICENSE
gitevo-0.1.3.dist-info/RECORD
