Metadata-Version: 2.4
Name: gitevo
Version: 0.1.3
Summary: Code evolution analysis for Git repositories
Project-URL: Homepage, https://github.com/andrehora/gitevo
Project-URL: Issues, https://github.com/andrehora/gitevo/issues
Author-email: Andre Hora <andrehoraa@gmail.com>
License-Expression: MIT
License-File: LICENSE
Classifier: Intended Audience :: Developers
Classifier: License :: OSI Approved :: MIT License
Classifier: Operating System :: OS Independent
Classifier: Programming Language :: Python :: 3
Classifier: Topic :: Software Development :: Quality Assurance
Requires-Python: >=3.9
Requires-Dist: gitpython==3.1.44
Requires-Dist: tree-sitter
Requires-Dist: tree-sitter-java
Requires-Dist: tree-sitter-javascript
Requires-Dist: tree-sitter-python
Requires-Dist: tree-sitter-typescript
Requires-Dist: treeminer==0.1.0
